[
  {
    "name": "abel",
    "id": 1,
    "image": "https://images.pexels.com/photos/1224158/pexels-photo-1224158.jpeg?auto=compress&cs=tinysrgb&dpr=2&h=750&w=1260"
  },
  {
    "name": "bella",
    "id": 2,
    "image": "https://images.pexels.com/photos/1224158/pexels-photo-1224158.jpeg?auto=compress&cs=tinysrgb&dpr=2&h=750&w=1260"
  },
  {
    "name": "collins",
    "id": 3,
    "image": "https://images.pexels.com/photos/1224158/pexels-photo-1224158.jpeg?auto=compress&cs=tinysrgb&dpr=2&h=750&w=1260"
  },
  {
    "name": "danny",
    "id": 4,
    "image": "https://images.pexels.com/photos/1224158/pexels-photo-1224158.jpeg?auto=compress&cs=tinysrgb&dpr=2&h=750&w=1260"
  },
  {
    "name": "edd",
    "id": 5,
    "image": "https://images.pexels.com/photos/1224158/pexels-photo-1224158.jpeg?auto=compress&cs=tinysrgb&dpr=2&h=750&w=1260"
  },
  {
    "name": "frankie",
    "id": 6,
    "image": "https://images.pexels.com/photos/1224158/pexels-photo-1224158.jpeg?auto=compress&cs=tinysrgb&dpr=2&h=750&w=1260"
  },
  {
    "name": "georgina",
    "id": 7,
    "image": "https://images.pexels.com/photos/1224158/pexels-photo-1224158.jpeg?auto=compress&cs=tinysrgb&dpr=2&h=750&w=1260"
  },
  {
    "name": "hardey",
    "id": 8,
    "image": "https://images.pexels.com/photos/1224158/pexels-photo-1224158.jpeg?auto=compress&cs=tinysrgb&dpr=2&h=750&w=1260"
  },
  {
    "name": "idris",
    "id": 9,
    "image": "https://images.pexels.com/photos/1224158/pexels-photo-1224158.jpeg?auto=compress&cs=tinysrgb&dpr=2&h=750&w=1260"
  },
  {
    "name": "jackie",
    "id": 10,
    "image": "https://images.pexels.com/photos/1224158/pexels-photo-1224158.jpeg?auto=compress&cs=tinysrgb&dpr=2&h=750&w=1260"
  },
  {
    "name": "kaleb",
    "id": 11,
    "image": "https://images.pexels.com/photos/1224158/pexels-photo-1224158.jpeg?auto=compress&cs=tinysrgb&dpr=2&h=750&w=1260"
  },
  {
    "name": "laura",
    "id": 12,
    "image": "https://images.pexels.com/photos/1224158/pexels-photo-1224158.jpeg?auto=compress&cs=tinysrgb&dpr=2&h=750&w=1260"
  },
  {
    "name": "moira",
    "id": 13,
    "image": "https://images.pexels.com/photos/1224158/pexels-photo-1224158.jpeg?auto=compress&cs=tinysrgb&dpr=2&h=750&w=1260"
  },
  {
    "name": "nadine",
    "id": 14,
    "image": "https://images.pexels.com/photos/1224158/pexels-photo-1224158.jpeg?auto=compress&cs=tinysrgb&dpr=2&h=750&w=1260"
  },
  {
    "name": "oscar",
    "id": 15,
    "image": "https://images.pexels.com/photos/1224158/pexels-photo-1224158.jpeg?auto=compress&cs=tinysrgb&dpr=2&h=750&w=1260"
  },
  {
    "name": "paulie",
    "id": 16,
    "image": "https://images.pexels.com/photos/1224158/pexels-photo-1224158.jpeg?auto=compress&cs=tinysrgb&dpr=2&h=750&w=1260"
  },
  {
    "name": "quentin",
    "id": 17,
    "image": "https://images.pexels.com/photos/1224158/pexels-photo-1224158.jpeg?auto=compress&cs=tinysrgb&dpr=2&h=750&w=1260"
  },
  {
    "name": "rhoda",
    "id": 18,
    "image": "https://images.pexels.com/photos/1224158/pexels-photo-1224158.jpeg?auto=compress&cs=tinysrgb&dpr=2&h=750&w=1260"
  },
  {
    "name": "samir",
    "id": 19,
    "image": "https://images.pexels.com/photos/1224158/pexels-photo-1224158.jpeg?auto=compress&cs=tinysrgb&dpr=2&h=750&w=1260"
  }
]